[
  {
    "id": "Câu 41",
    "question_text": "Kim loại nào sau đây không tác dụng với dung dịch CuCl2?",
    "options": {
      "A": "Mg.",
      "B": "Ag.",
      "C": "Fe.",
      "D": "Zn."
    }
  },
  {
    "id": "Câu 42",
    "question_text": "Kim loại nào sau đây tan được trong dung dịch kiềm ?",
    "options": {
      "A": "Cu.",
      "B": "Fe.",
      "C": "Mg.",
      "D": "Al."
    }
  },
  {
    "id": "Câu 43",
    "question_text": "Cách bảo quản thực phẩm (thịt, cá…) bằng cách nào sau đây được coi là an toàn là dùng nước đá hay nước đá khô.",
    "options": {
      "A": "Ngâm trong dung dịch HCHO.",
      "B": "Ngâm trong nước muối.",
      "C": "Dùng nước đá khô.",
      "D": "Phun dung dịch ure."
    }
  },
  {
    "id": "Câu 44",
    "question_text": "Dung dịch chất nào sau đây có phản ứng màu biure?",
    "options": {
      "A": "Glyxin.",
      "B": "Alanin.",
      "C": "Valin.",
      "D": "Val-Gly-Ala."
    }
  },
  {
    "id": "Câu 45",
    "question_text": "Kim loại nào sau đây tác dụng với H2O ở nhiệt độ thường?",
    "options": {
      "A": "Mg.",
      "B": "Al.",
      "C": "Ca.",
      "D": "Fe."
    }
  },
  {
    "id": "Câu 46",
    "question_text": "Phát biểu nào sau đây không đúng?",
    "options": {
      "A": "Dung dịch fomon dùng để ngâm xác động vật.",
      "B": "Nhỏ dung dịch I2 vào hồ tinh bột thấy xuất hiện màu xanh tím.",
      "C": "Anilin là chất lỏng, tan nhiều trong nước.",
      "D": "Chất béo nhẹ hơn nước, không tan trong nước."
    }
  },
  {
    "id": "Câu 47",
    "question_text": "Chất nào sau đây không có phản ứng trùng hợp?",
    "options": {
      "A": "Axetilen.",
      "B": "Etilen.",
      "C": "Isopren.",
      "D": "Benzen."
    }
  },
  {
    "id": "Câu 48",
    "question_text": "Nước cứng tạm thời có chứa các ion nào sau đây?",
    "options": {
      "A": "Ca2+, Mg2+, Cl-.",
      "B": "Ca2+, Mg2+, HCO3-.",
      "C": "Ca2+, Mg2+, SO42-.",
      "D": "Ca2+, Mg2+, Cl-, SO42-."
    }
  },
  {
    "id": "Câu 49",
    "question_text": "Thủy phân este X có công thức phân tử C4H8O2 (trong môi trường axit) thu được ancol etylic. Tên gọi của X là:",
    "options": {
      "A": "Etyl fomat.",
      "B": "Metyl propionat.",
      "C": "Etyl axetat.",
      "D": "Propyl axetat."
    }
  },
  {
    "id": "Câu 50",
    "question_text": "Nhóm kim loại nào sau đây được xếp theo chiều tăng dần tính khử?",
    "options": {
      "A": "Fe, Zn, Al.",
      "B": "Al, Zn, Fe.",
      "C": "Al, Fe, Zn.",
      "D": "Fe, Al, Zn."
    }
  },
  {
    "id": "Câu 51",
    "question_text": "Phản ứng hóa học xảy ra trong quá trình ăn mòn kim loại thuộc loại",
    "options": {
      "A": "phản ứng thế.",
      "B": "phản ứng oxi hóa – khử.",
      "C": "phản ứng trao đổi.",
      "D": "phản ứng phân hủy."
    }
  },
  {
    "id": "Câu 52",
    "question_text": "Chất nào sau đây có tính lưỡng tính?",
    "options": {
      "A": "AlCl3.",
      "B": "NaHCO3.",
      "C": "Al2O3.",
      "D": "CrO3."
    }
  },
  {
    "id": "Câu 53",
    "question_text": "Thủy phân hoàn toàn 1 mol tripeptit X (mạch hở), thu được 2 mol glyxin và 1 mol alanin. X có tối đa bao nhiêu công thức cấu tạo?",
    "options": {
      "A": "2.",
      "B": "4.",
      "C": "3.",
      "D": "5."
    }
  },
  {
    "id": "Câu 54",
    "question_text": "Chất nào sau đây phản ứng với Cu(OH)2/OH- ở nhiệt độ thường tạo thành dung dịch màu xanh lam?",
    "options": {
      "A": "Glucozơ.",
      "B": "Tinh bột.",
      "C": "Anđehit axetic.",
      "D": "Ancol etylic."
    }
  },
  {
    "id": "Câu 55",
    "question_text": "Kim loại nào sau đây điều chế bằng phương pháp nhiệt luyện?",
    "options": {
      "A": "Na.",
      "B": "Ca.",
      "C": "Fe.",
      "D": "Ba."
    }
  },
  {
    "id": "Câu 56",
    "question_text": "Chất nào sau đây dùng để làm mềm nước có tính cứng vĩnh cửu?",
    "options": {
      "A": "Na3PO4.",
      "B": "HCl.",
      "C": "NaCl.",
      "D": "Ca(OH)2."
    }
  },
  {
    "id": "Câu 57",
    "question_text": "Tơ nilon-6,6 được điều chế bằng phản ứng",
    "options": {
      "A": "Trùng hợp vinyl xianua.",
      "B": "Trùng ngưng axit $\\alpha$-aminocaproic.",
      "C": "Trùng hợp metyl metacrylat.",
      "D": "Trùng ngưng hexametylenđiamin và axit ađip"
    }
}
]